dt_sbom_scanner/AnsiColors.py
dt_sbom_scanner/__init__.py
dt_sbom_scanner/sbom_utils.py
dt_sbom_scanner/scan.py
dt_sbom_scanner-1.9.0.dist-info/METADATA
dt_sbom_scanner-1.9.0.dist-info/WHEEL
dt_sbom_scanner-1.9.0.dist-info/entry_points.txt
dt_sbom_scanner-1.9.0.dist-info/licenses/LICENSE.txt
dt_sbom_scanner-1.9.0.dist-info/RECORD
