Metadata-Version: 2.4
Name: dt-sbom-scanner
Version: 1.9.0
Summary: Dependency Track SBOM Scanner
License-Expression: MIT
License-File: LICENSE.txt
Keywords: tool,sbom,dependency track
Author: Pierre Smeyers
Author-email: pierre.smeyers@gmail.com
Requires-Python: >=3.12,<4.0
Classifier: Development Status :: 4 - Beta
Classifier: Environment :: Console
Classifier: Intended Audience :: Developers
Classifier: License :: OSI Approved :: MIT License
Classifier: Operating System :: OS Independent
Classifier: Programming Language :: Python
Classifier: Programming Language :: Python :: 3
Classifier: Programming Language :: Python :: 3.12
Classifier: Programming Language :: Python :: 3.13
Classifier: Programming Language :: Python :: 3.14
Classifier: Programming Language :: Python :: 3 :: Only
Requires-Dist: cyclonedx-python-lib (>=11.1.0,<12.0.0)
Requires-Dist: requests (>=2.32.5,<4.0.0)
Requires-Dist: urllib3 (>=2.6.0,<3.0.0)
Project-URL: Homepage, https://gitlab.com/to-be-continuous/tools/dt-sbom-scanner
Project-URL: Issues, https://gitlab.com/to-be-continuous/tools/dt-sbom-scanner/-/issues
